README.rst
setup.py
ctf_cli/__init__.py
ctf_cli/application.py
ctf_cli/arguments_parser.py
ctf_cli/behave.py
ctf_cli/cli_runner.py
ctf_cli/common_environment.py
ctf_cli/config.py
ctf_cli/exceptions.py
ctf_cli/logger.py
ctf_cli/settings.py
ctf_cli/version.py
ctf_cli.egg-info/PKG-INFO
ctf_cli.egg-info/SOURCES.txt
ctf_cli.egg-info/dependency_links.txt
ctf_cli.egg-info/entry_points.txt
ctf_cli.egg-info/requires.txt
ctf_cli.egg-info/top_level.txt