Metadata-Version: 1.1
Name: ctf-cli
Version: 1.0.2
Summary: Simple command line tool for executing Containers Testing Framework
Home-page: https://github.com/Containers-Testing-Framework/ctf-cli
Author: Vadim Rutkovsky
Author-email: vrutkovs@redhat.com
License: GPLv2
Download-URL: https://github.com/Containers-Testing-Framework/ctf-cli/archive/1.0.2.tar.gz
Keywords: docker behave
Platform: UNKNOWN
